{"cameraMode":{"drawMode":0,"name":"Shaded","section":"Shading Mode"},"sceneLighting":false,"audioPlay":false,"sceneViewState":{"m_AlwaysRefresh":false,"showFog":false,"showSkybox":false,"showFlares":false,"showImageEffects":false,"showParticleSystems":false,"showVisualEffectGraphs":true,"m_FxEnabled":false},"in2DMode":false,"pivot":{"x":27.292200088500978,"y":-1.1525077819824219,"z":-36.458900451660159},"rotation":{"x":0.029348595067858697,"y":-0.9696128964424133,"z":0.19301964342594148,"w":0.14743457734584809},"size":10.0,"orthographic":false}